LICENSE
MANIFEST.in
README.md
setup.cfg
setup.py
django_nameko/VERSION
django_nameko/__init__.py
django_nameko/rpc.py
django_nameko.egg-info/PKG-INFO
django_nameko.egg-info/SOURCES.txt
django_nameko.egg-info/dependency_links.txt
django_nameko.egg-info/not-zip-safe
django_nameko.egg-info/requires.txt
django_nameko.egg-info/top_level.txt