Metadata-Version: 1.2
Name: django-nameko
Version: 0.5.3
Summary:  Django wrapper for nameko microservice framework.
Home-page: http://github.com/and3rson/django-nameko
Author: Andrew Dunai
Author-email: andrew@dun.ai
Maintainer: Vincent Anh Tran
Maintainer-email: tranvietanh1991@gmail.com
License: GPLv2
Platform: UNKNOWN
